{
  "display": {
    "icon": {
      "item": "rubin:rubin"
    },
    "title": {
      "translate": "advancements.dostizhieniia.title"
    },
    "description": {
      "translate": "advancements.dostizhieniia.descr"
    },
    "frame": "task",
    "show_toast": true,
    "announce_to_chat": true,
    "hidden": false
  },
  "criteria": {
    "dostizhieniia": {
      "trigger": "minecraft:inventory_changed",
      "conditions": {
        "items": [
          {
            "item": "rubin:rubin",
            "count": {
              "min": 1,
              "max": 1
            }
          }
        ]
      }
    }
  },
  "rewards": {
    "experience": 5,
    "recipes": [
      "rubin:deleted_mod_element",
      "rubin:deleted_mod_element",
      "rubin:deleted_mod_element",
      "rubin:deleted_mod_element",
      "rubin:deleted_mod_element",
      "rubin:deleted_mod_element",
      "rubin:deleted_mod_element",
      "rubin:deleted_mod_element",
      "rubin:deleted_mod_element",
      "rubin:deleted_mod_element",
      "rubin:deleted_mod_element",
      "rubin:deleted_mod_element",
      "rubin:deleted_mod_element"
    ]
  },
  "parent": "minecraft:nether/obtain_ancient_debris"
}